issuebadge/__init__.py
issuebadge/py.typed
digitalbadge-1.0.1.dist-info/LICENSE
digitalbadge-1.0.1.dist-info/METADATA
digitalbadge-1.0.1.dist-info/WHEEL
digitalbadge-1.0.1.dist-info/top_level.txt
digitalbadge-1.0.1.dist-info/RECORD
