Metadata-Version: 2.1
Name: digitalbadge
Version: 1.0.1
Summary: Python SDK for digital badge and certificate generation. Create, issue, and manage digital certificates and badges at scale.
Author-email: Issue Badge <support@issuebadge.com>
Maintainer-email: Issue Badge <support@issuebadge.com>
License: MIT
Project-URL: Homepage, https://issuebadge.com
Project-URL: Documentation, https://issuebadge.com/h/developer
Project-URL: Repository, https://github.com/issuebadge/sdk
Project-URL: Bug Tracker, https://github.com/issuebadge/sdk/issues
Project-URL: Changelog, https://github.com/issuebadge/sdk/releases
Keywords: issuebadge,issue badge,certificate generator,bulk certificate generator,digital badge,digital certificate,badge generator,certificate maker,certificate creator,badge creator,credential management,certificate automation,online certificate,e-certificate,award certificate,achievement badge,training certificate,course certificate,completion certificate,certificate API,badge API,verifiable credentials,open badge,badge issuer,certificate issuer,HR certificate,employee certificate,student cer
Classifier: Development Status :: 5 - Production/Stable
Classifier: Intended Audience :: Developers
Classifier: Intended Audience :: Education
Classifier: Intended Audience :: Information Technology
Classifier: License :: OSI Approved :: MIT License
Classifier: Operating System :: OS Independent
Classifier: Programming Language :: Python :: 3
Classifier: Programming Language :: Python :: 3.6
Classifier: Programming Language :: Python :: 3.7
Classifier: Programming Language :: Python :: 3.8
Classifier: Programming Language :: Python :: 3.9
Classifier: Programming Language :: Python :: 3.10
Classifier: Programming Language :: Python :: 3.11
Classifier: Programming Language :: Python :: 3.12
Classifier: Topic :: Education
Classifier: Topic :: Internet :: WWW/HTTP :: Dynamic Content
Classifier: Topic :: Office/Business
Classifier: Topic :: Software Development :: Libraries :: Python Modules
Classifier: Typing :: Typed
Requires-Python: >=3.6
License-File: LICENSE
Requires-Dist: requests>=2.20.0
Provides-Extra: dev
Requires-Dist: pytest>=6.0; extra == "dev"
Requires-Dist: pytest-cov>=2.0; extra == "dev"
